[
  {
    "name": "Tech Team",
    "description": "Lorem ipsum dolor sit amet, consectetur adipiscing elit. Nullam enim nunc, bibendum fringilla leo ac.",
    "lookingFor": "description of skills of person which want to join team",
    "technologies": ["JavaScript", "Flutter", "Artificial intelligence"],
    "contact": {
      "discord": "discord.chanel.url",
      "messanger": "messanger.team.url",
      "telegram": "telegram.team.url",
      "mail": "mail.team.url",
      "phone": 123456789
    },
    "members": [
      {"name": "name or alias", "avatarUrl": "./assets/images/default-avatar.webp", "url": "someUrl"},
      {"name": "name or alias", "avatarUrl": "./assets/images/default-avatar.webp", "url": "someUrl"}
    ]
  },
  {
    "name": "Tech Talk Team",
    "description": "Lorem ipsum dolor sit amet, consectetur adipiscing elit. Nullam enim nunc, bibendum fringilla leo ac.",
    "lookingFor": "description of skills of person which want to join team",
    "technologies": ["Linkedin", "Tech Talks"],
    "contact": {
      "discord": "discord.chanel.url",
      "messanger": "messanger.team.url",
      "telegram": "telegram.team.url",
      "mail": "mail.team.url",
      "phone": 123456789
    },
    "members": [
      {"name": "name or alias", "avatarUrl": "./assets/images/default-avatar.webp", "url": "someUrl"},
      {"name": "name or alias", "avatarUrl": "./assets/images/default-avatar.webp", "url": "someUrl"}
    ]
  },
  {
    "name": "Creative Marketing Team",
    "description": "Lorem ipsum dolor sit amet, consectetur adipiscing elit. Nullam enim nunc, bibendum fringilla leo ac.",
    "lookingFor": "description of skills of person which want to join team",
    "technologies": ["Instagram", "Canva", "Marketing"],
    "contact": {
      "discord": "discord.chanel.url",
      "messanger": "messanger.team.url",
      "telegram": "telegram.team.url",
      "mail": "mail.team.url",
      "phone": 123456789
    },
    "members": [
      {"name": "Tajwar Haque", "avatarUrl": "./assets/images/default-avatar.webp", "url": "someUrl"},
      {"name": "Nashrah", "avatarUrl": "./assets/images/default-avatar.webp", "url": "someUrl"},
      {"name": "Samin Enam", "avatarUrl": "./assets/images/default-avatar.webp", "url": "someUrl"},
      {"name": "Name or alias", "avatarUrl": "./assets/images/default-avatar.webp", "url": "someUrl"}
    ]
  },
  {
    "name": "Community Team",
    "description": "Lorem ipsum dolor sit amet, consectetur adipiscing elit. Nullam enim nunc, bibendum fringilla leo ac.",
    "lookingFor": "description of skills of person which want to join team",
    "technologies": ["Interactivity", "Open-Mindedness", "Fun Events"],
    "contact": {
      "discord": "discord.chanel.url",
      "messanger": "messanger.team.url",
      "telegram": "telegram.team.url",
      "mail": "mail.team.url",
      "phone": 123456789
    },
    "members": [
      {"name": "name or alias", "avatarUrl": "./assets/images/default-avatar.webp", "url": "someUrl"},
      {"name": "name or alias", "avatarUrl": "./assets/images/default-avatar.webp", "url": "someUrl"}
    ]
  }
]